MANIFEST.in
README.txt
setup.py
backitup/__init__.py
backitup.egg-info/PKG-INFO
backitup.egg-info/SOURCES.txt
backitup.egg-info/dependency_links.txt
backitup.egg-info/top_level.txt
examples/run_weekly.py
examples/yourhelper.py