Metadata-Version: 1.0
Name: backitup
Version: 0.9.5
Summary: Simply library for easily customized backup and uploading of your files
Home-page: http://code.google.com/p/backitup/
Author: Rob Galanakis
Author-email: rob.galanakis@gmail.com
License: MIT
Download-URL: http://pypi.python.org/pypi/backitup
Keywords: archive,backup,upload
Platform: POSIX
Platform: Windows
Classifier: Programming Language :: Python
Classifier: Operating System :: OS Independent
Classifier: License :: OSI Approved :: MIT License
Classifier: Development Status :: 4 - Beta
Classifier: Topic :: Software Development :: Libraries :: Python Modules
Classifier: Topic :: System :: Archiving
Classifier: Topic :: System :: Archiving :: Backup
Classifier: Intended Audience :: End Users/Desktop
Classifier: Intended Audience :: Developers
Classifier: Intended Audience :: Information Technology
Classifier: Intended Audience :: System Administrators
